mjc_viewer/__init__.py
mjc_viewer/py.typed
mjc_viewer/_src/__init__.py
mjc_viewer/_src/config.proto
mjc_viewer/_src/config_pb2.py
mjc_viewer/_src/config_pb2.pyi
mjc_viewer/_src/serializer.py
mjc_viewer/_src/trajectory.py
mjc_viewer/_src/js/animator.js
mjc_viewer/_src/js/selector.js
mjc_viewer/_src/js/system.js
mjc_viewer/_src/js/viewer.js
mjc_viewer-0.0.5.dist-info/LICENSE
mjc_viewer-0.0.5.dist-info/METADATA
mjc_viewer-0.0.5.dist-info/WHEEL
mjc_viewer-0.0.5.dist-info/top_level.txt
mjc_viewer-0.0.5.dist-info/zip-safe
mjc_viewer-0.0.5.dist-info/RECORD
