Metadata-Version: 2.1
Name: mjc-viewer
Version: 0.0.5
Summary: A browser-based 3D viewer for MuJoCo
Home-page: https://github.com/kevinzakka/mjc_viewer
Author: Kevin Zakka
Author-email: kevinarmandzakka@gmail.com
Maintainer: Kevin Zakka
Maintainer-email: kevinarmandzakka@gmail.com
License: MIT
Classifier: Development Status :: 3 - Alpha
Classifier: Intended Audience :: Developers
Classifier: Intended Audience :: Science/Research
Classifier: License :: OSI Approved :: MIT License
Classifier: Natural Language :: English
Classifier: Programming Language :: Python :: 3
Classifier: Programming Language :: Python :: 3.7
Classifier: Programming Language :: Python :: 3.8
Classifier: Programming Language :: Python :: 3.9
Classifier: Topic :: Scientific/Engineering :: Artificial Intelligence
Requires-Python: >=3.7
License-File: LICENSE
Requires-Dist: mujoco (>=2.2.0)
Requires-Dist: numpy
Requires-Dist: dm-control (>=1.0.1)
Requires-Dist: dm-robotics-transformations
Requires-Dist: protobuf (>=4.21.2)
Provides-Extra: examples
Requires-Dist: dcargs (>=0.1.3) ; extra == 'examples'
